LICENSE
MANIFEST.in
README.rst
setup.cfg
setup.py
versioneer.py
src/pmx/__init__.py
src/pmx/_version.py
src/pmx/alchemy.py
src/pmx/analysis.py
src/pmx/atom.py
src/pmx/atomselection.py
src/pmx/builder.py
src/pmx/chain.py
src/pmx/estimators.py
src/pmx/ffparser.py
src/pmx/forcefield.py
src/pmx/geometry.py
src/pmx/gmx.py
src/pmx/jobscript.py
src/pmx/library.py
src/pmx/ligand_alchemy.py
src/pmx/model.py
src/pmx/molecule.py
src/pmx/mutdb.py
src/pmx/ndx.py
src/pmx/options.py
src/pmx/parser.py
src/pmx/rotamer.py
src/pmx/utils.py
src/pmx/xdrfile.py
src/pmx/xtc.py
src/pmx/data/aminoacids.pkl
src/pmx/data/bbdep.pkl
src/pmx/data/blosum62_new.mat
src/pmx/data/bp.pkl
src/pmx/data/bp_amber.pkl
src/pmx/data/bp_charmm.pkl
src/pmx/data/rna.pkl
src/pmx/data/mutff/atommass.dat
src/pmx/data/mutff/elements.dat
src/pmx/data/mutff/residuetypes.dat
src/pmx/data/mutff/spc216.gro
src/pmx/data/mutff/specbond.dat
src/pmx/data/mutff/vdwradii.dat
src/pmx/data/mutff/xlateat.dat
src/pmx/data/mutff/amber14sbmut.ff/Makefile.am
src/pmx/data/mutff/amber14sbmut.ff/Makefile.in
src/pmx/data/mutff/amber14sbmut.ff/aminoacids.arn
src/pmx/data/mutff/amber14sbmut.ff/aminoacids.c.tdb
src/pmx/data/mutff/amber14sbmut.ff/aminoacids.hdb
src/pmx/data/mutff/amber14sbmut.ff/aminoacids.n.tdb
src/pmx/data/mutff/amber14sbmut.ff/aminoacids.r2b
src/pmx/data/mutff/amber14sbmut.ff/aminoacids.rtp
src/pmx/data/mutff/amber14sbmut.ff/aminoacids.vsd
src/pmx/data/mutff/amber14sbmut.ff/atomtypes.atp
src/pmx/data/mutff/amber14sbmut.ff/dna.arn
src/pmx/data/mutff/amber14sbmut.ff/dna.hdb
src/pmx/data/mutff/amber14sbmut.ff/dna.r2b
src/pmx/data/mutff/amber14sbmut.ff/dna.rtp
src/pmx/data/mutff/amber14sbmut.ff/ffbonded.itp
src/pmx/data/mutff/amber14sbmut.ff/ffnonbonded.itp
src/pmx/data/mutff/amber14sbmut.ff/forcefield.doc
src/pmx/data/mutff/amber14sbmut.ff/forcefield.itp
src/pmx/data/mutff/amber14sbmut.ff/gbsa.itp
src/pmx/data/mutff/amber14sbmut.ff/ions.itp
src/pmx/data/mutff/amber14sbmut.ff/mutres.mtp
src/pmx_satumut.egg-info/PKG-INFO
src/pmx_satumut.egg-info/SOURCES.txt
src/pmx_satumut.egg-info/dependency_links.txt
src/pmx_satumut.egg-info/entry_points.txt
src/pmx_satumut.egg-info/not-zip-safe
src/pmx_satumut.egg-info/requires.txt
src/pmx_satumut.egg-info/top_level.txt