Metadata-Version: 2.1
Name: pmx-satumut
Version: 2.0.4
Summary: Toolkit for free-energy calculation setup/analysis and biomolecular structure handling
Home-page: https://github.com/AlbertCS/pmx-satumut/tree/develop
Author: Daniel Seeliger
Author-email: seeliger.biosoft@gmail.de
License: GPL 3
Platform: UNKNOWN
Classifier: Development Status :: 3 - Alpha
Classifier: License :: OSI Approved :: GNU General Public License (GPL)
Classifier: Programming Language :: Python
Classifier: Intended Audience :: Science/Research
Classifier: Topic :: Scientific/Engineering
Requires-Python: >=3.6
License-File: LICENSE
